trep/config.py
trep/constraint.py
trep/finput.py
trep/force.py
trep/frame.py
trep/midpointvi.py
trep/potential.py
trep/pthreadGC2.dll
trep/spline.py
trep/system.py
trep/tapemeasure.py
trep/util.py
trep/_trep.pyd
trep/__init__.py
trep/__version__.py
trep/constraints/distance.py
trep/constraints/plane.py
trep/constraints/point.py
trep/constraints/__init__.py
trep/discopt/dcost.py
trep/discopt/dlqr.py
trep/discopt/doptimizer.py
trep/discopt/dsystem.py
trep/discopt/__init__.py
trep/forces/bodywrench.py
trep/forces/configforce.py
trep/forces/damping.py
trep/forces/hybridwrench.py
trep/forces/lineardamper.py
trep/forces/spatialwrench.py
trep/forces/testforce.py
trep/forces/__init__.py
trep/potentials/configspring.py
trep/potentials/gravity.py
trep/potentials/linearspring.py
trep/potentials/nonlinear_config_spring.py
trep/potentials/template.py
trep/potentials/__init__.py
trep/puppets/puppets.py
trep/puppets/__init__.py
trep/ros/ros_mvi.py
trep/ros/urdf_parser.py
trep/ros/__init__.py
trep/visual/polyobject.py
trep/visual/splineplotter.py
trep/visual/stlmodel.py
trep/visual/timelinewidget.py
trep/visual/view2d.py
trep/visual/view3d.py
trep/visual/visual.py
trep/visual/visualitem.py
trep/visual/visualscene.py
trep/visual/_polyobject.pyd
trep/visual/__init__.py
trep/visual/icons/playback-frame-backward.svg
trep/visual/icons/playback-frame-forward.svg
trep/visual/icons/playback-jump-backward.svg
trep/visual/icons/playback-jump-forward.svg
trep/visual/icons/playback-pause.svg
trep/visual/icons/playback-play.svg
trep/visual/icons/playback-skip-backward.svg
trep/visual/icons/playback-skip-forward.svg
trep/visual/icons/playback-stop.svg
trep-1.0.2.data/headers/c_api.h
trep-1.0.2.data/headers/trep.h
trep-1.0.2.dist-info/DESCRIPTION.rst
trep-1.0.2.dist-info/METADATA
trep-1.0.2.dist-info/metadata.json
trep-1.0.2.dist-info/RECORD
trep-1.0.2.dist-info/top_level.txt
trep-1.0.2.dist-info/WHEEL
