Metadata-Version: 2.0
Name: trep
Version: 1.0.2
Summary: trep is used to simulate mechanical systems.
Home-page: http://murpheylab.github.io/trep/
Author: Elliot Johnson
Author-email: elliot.r.johnson@gmail.com
License: GPLv3
Platform: Linux
Platform: Mac
Platform: Windows
Requires-Dist: numpy
Requires-Dist: scipy
